easy_post_twitter/__init__.py
easy_post_twitter/twitter.py
easy_post_twitter-1.0.8.dist-info/METADATA
easy_post_twitter-1.0.8.dist-info/WHEEL
easy_post_twitter-1.0.8.dist-info/RECORD
