Metadata-Version: 2.1
Name: easy-post-twitter
Version: 1.0.8
Summary: The easy way to send posts to twitter.
Author: Thiago Oliveira
Author-email: thiceconelo@gmail.com
Requires-Python: >=3.8,<4.0
Classifier: Programming Language :: Python :: 3
Classifier: Programming Language :: Python :: 3.8
Classifier: Programming Language :: Python :: 3.9
Classifier: Programming Language :: Python :: 3.10
Classifier: Programming Language :: Python :: 3.11
Requires-Dist: loguru (>=0.6.0,<0.7.0)
Requires-Dist: python-dotenv (>=0.20.0,<0.21.0)
Requires-Dist: tweepy (>=4.14.0,<5.0.0)
